muc/__init__.py
muc/subscriptable_set.py
myusefulclasses-0.0.1.dist-info/METADATA
myusefulclasses-0.0.1.dist-info/WHEEL
myusefulclasses-0.0.1.dist-info/top_level.txt
myusefulclasses-0.0.1.dist-info/RECORD
