Metadata-Version: 2.1
Name: myusefulclasses
Version: 0.0.1
Summary: Some useful helper classes
Home-page: https://gitlab.com/kikulacho92/myusefulclasses
Author: Emiliano Minerba
Author-email: emi.nerba@gmail.com
License: GPL
Platform: UNKNOWN
Requires-Dist: wheel
